{
	"/api.html": {
		"hash": "denAB5050Z-KfKNkHSBuDMhh5AA",
		"delta": 0,
		"size": 41971
	},
	"/changelog.html": {
		"hash": "hajAUfKIE_WxVcOC-ZPRvIEWaUU",
		"delta": 0,
		"size": 30043
	},
	"/config.html": {
		"hash": "Z3dQwdmpq49t4oPmGunBqRxkKKg",
		"delta": 0,
		"size": 37781
	},
	"/convention.html": {
		"hash": "rSWglLM4ZkjaqSpbkpxCyiKmMZw",
		"delta": 0,
		"size": 21129
	},
	"/function-mocks.html": {
		"hash": "7MnOiUvncaWmLKMLgiHQ6AtHW8Q",
		"delta": 0,
		"size": 28912
	},
	"/index.html": {
		"hash": "cFpIVxzp-weG2hGh7ucOHJd7UUo",
		"delta": 0,
		"size": 30561
	},
	"/installation.html": {
		"hash": "FHKwTADgidu2CDnCWMfROSB2V44",
		"delta": -1,
		"size": 22628
	},
	"/plugins.html": {
		"hash": "XQ9EYgVHS0oqbm7VEXSkzAOu87U",
		"delta": 0,
		"size": 24240
	},
	"/privacy-and-security.html": {
		"hash": "8IouhFt1HBDUr_Z31ua_dePi_m4",
		"delta": 0,
		"size": 18848
	},
	"/related-tech.html": {
		"hash": "vsVeTU3GK_IFAOm5DrmmDkwQ7r0",
		"delta": 0,
		"size": 19987
	},
	"/scraping.html": {
		"hash": "laO5NV0rI0DU86lACYz9nB4HQOU",
		"delta": 0,
		"size": 19554
	},
	"/use-cases.html": {
		"hash": "VEDRR1rI3voL2UMbOABTaBN8hQ4",
		"delta": 0,
		"size": 20914
	},
	"/vite.html": {
		"hash": "gqRyOdbVXoqw2Zjl1ndDpkhYoUk",
		"delta": 0,
		"size": 20160
	}
}